{
  "extraction_timestamp": "2025-07-20T09:07:41.269091",
  "manufacturer": "Skylon Archery",
  "extraction_range": {
    "start_index": 0,
    "end_index": 21,
    "total_urls_available": 21,
    "urls_processed": 21
  },
  "statistics": {
    "processed": 21,
    "successful": 20,
    "arrows": 20
  },
  "success_rate": 95.23809523809523,
  "total_arrows": 20,
  "total_spine_specs": 153,
  "arrows": [
    {
      "manufacturer": "Skylon Archery",
      "model_name": "Performa",
      "spine_specifications": [
        {
          "spine": 350,
          "outer_diameter": 0.207,
          "gpi_weight": 8.47,
          "inner_diameter": 0.125,
          "length_options": [
            32.0
          ]
        },
        {
          "spine": 400,
          "outer_diameter": 0.204,
          "gpi_weight": 7.93,
          "inner_diameter": 0.125,
          "length_options": [
            32.0
          ]
        },
        {
          "spine": 450,
          "outer_diameter": 0.198,
          "gpi_weight": 7.42,
          "inner_diameter": 0.125,
          "length_options": [
            32.0
          ]
        },
        {
          "spine": 500,
          "outer_diameter": 0.193,
          "gpi_weight": 6.9,
          "inner_diameter": 0.125,
          "length_options": [
            32.0
          ]
        },
        {
          "spine": 550,
          "outer_diameter": 0.191,
          "gpi_weight": 6.5,
          "inner_diameter": 0.125,
          "length_options": [
            32.0
          ]
        },
        {
          "spine": 600,
          "outer_diameter": 0.188,
          "gpi_weight": 6.1,
          "inner_diameter": 0.125,
          "length_options": [
            32.0
          ]
        },
        {
          "spine": 650,
          "outer_diameter": 0.186,
          "gpi_weight": 5.83,
          "inner_diameter": 0.125,
          "length_options": [
            31.0
          ]
        },
        {
          "spine": 700,
          "outer_diameter": 0.184,
          "gpi_weight": 5.55,
          "inner_diameter": 0.125,
          "length_options": [
            31.0
          ]
        },
        {
          "spine": 750,
          "outer_diameter": 0.182,
          "gpi_weight": 5.31,
          "inner_diameter": 0.125,
          "length_options": [
            31.0
          ]
        },
        {
          "spine": 800,
          "outer_diameter": 0.181,
          "gpi_weight": 5.06,
          "inner_diameter": 0.125,
          "length_options": [
            31.0
          ]
        },
        {
          "spine": 850,
          "outer_diameter": 0.179,
          "gpi_weight": 4.94,
          "inner_diameter": 0.125,
          "length_options": [
            30.0
          ]
        },
        {
          "spine": 900,
          "outer_diameter": 0.177,
          "gpi_weight": 4.81,
          "inner_diameter": 0.125,
          "length_options": [
            30.0
          ]
        },
        {
          "spine": 1000,
          "outer_diameter": 0.175,
          "gpi_weight": 4.7,
          "inner_diameter": 0.125,
          "length_options": [
            30.0
          ]
        }
      ],
      "material": "40-TON Carbon",
      "carbon_content": null,
      "arrow_type": "target",
      "recommended_use": null,
      "description": "Ideal arrow with smaller diameter for less wind drift, high density carbon construction, and full length shaft.",
      "straightness_tolerance": null,
      "weight_tolerance": null,
      "price_range": null,
      "availability": null,
      "source_url": "https://www.skylonarchery.com/arrows/id-3-2/performa",
      "scraped_at": "2025-07-20T08:59:17.025275",
      "scraper_version": "1.0"
    },
    {
      "manufacturer": "Skylon Archery",
      "model_name": "Precium",
      "spine_specifications": [
        {
          "spine": 350,
          "outer_diameter": 0.207,
          "gpi_weight": 8.47,
          "inner_diameter": 0.125,
          "length_options": [
            32.0
          ]
        },
        {
          "spine": 400,
          "outer_diameter": 0.204,
          "gpi_weight": 7.93,
          "inner_diameter": 0.125,
          "length_options": [
            32.0
          ]
        },
        {
          "spine": 450,
          "outer_diameter": 0.198,
          "gpi_weight": 7.42,
          "inner_diameter": 0.125,
          "length_options": [
            32.0
          ]
        },
        {
          "spine": 500,
          "outer_diameter": 0.193,
          "gpi_weight": 6.9,
          "inner_diameter": 0.125,
          "length_options": [
            32.0
          ]
        },
        {
          "spine": 550,
          "outer_diameter": 0.191,
          "gpi_weight": 6.5,
          "inner_diameter": 0.125,
          "length_options": [
            32.0
          ]
        },
        {
          "spine": 600,
          "outer_diameter": 0.188,
          "gpi_weight": 6.1,
          "inner_diameter": 0.125,
          "length_options": [
            32.0
          ]
        },
        {
          "spine": 650,
          "outer_diameter": 0.186,
          "gpi_weight": 5.83,
          "inner_diameter": 0.125,
          "length_options": [
            31.0
          ]
        },
        {
          "spine": 700,
          "outer_diameter": 0.184,
          "gpi_weight": 5.55,
          "inner_diameter": 0.125,
          "length_options": [
            31.0
          ]
        },
        {
          "spine": 750,
          "outer_diameter": 0.182,
          "gpi_weight": 5.31,
          "inner_diameter": 0.125,
          "length_options": [
            31.0
          ]
        },
        {
          "spine": 800,
          "outer_diameter": 0.181,
          "gpi_weight": 5.06,
          "inner_diameter": 0.125,
          "length_options": [
            31.0
          ]
        },
        {
          "spine": 850,
          "outer_diameter": 0.179,
          "gpi_weight": 4.94,
          "inner_diameter": 0.125,
          "length_options": [
            30.0
          ]
        },
        {
          "spine": 900,
          "outer_diameter": 0.177,
          "gpi_weight": 4.81,
          "inner_diameter": 0.125,
          "length_options": [
            30.0
          ]
        },
        {
          "spine": 1000,
          "outer_diameter": 0.175,
          "gpi_weight": 4.7,
          "inner_diameter": 0.125,
          "length_options": [
            30.0
          ]
        }
      ],
      "material": "40-TON Carbon",
      "carbon_content": null,
      "arrow_type": "target",
      "recommended_use": null,
      "description": "Ideal arrow for target archery with smaller diameter for less wind drift and high-density carbon construction.",
      "straightness_tolerance": null,
      "weight_tolerance": null,
      "price_range": null,
      "availability": null,
      "source_url": "https://www.skylonarchery.com/arrows/id-3-2/precium",
      "scraped_at": "2025-07-20T08:59:54.991137",
      "scraper_version": "1.0"
    },
    {
      "manufacturer": "Skylon Archery",
      "model_name": "Paragon",
      "spine_specifications": [
        {
          "spine": 350,
          "outer_diameter": 0.2067,
          "gpi_weight": 8.47,
          "inner_diameter": 0.125,
          "length_options": [
            32.0
          ]
        },
        {
          "spine": 400,
          "outer_diameter": 0.2035,
          "gpi_weight": 7.93,
          "inner_diameter": 0.125,
          "length_options": [
            32.0
          ]
        },
        {
          "spine": 450,
          "outer_diameter": 0.1984,
          "gpi_weight": 7.42,
          "inner_diameter": 0.125,
          "length_options": [
            32.0
          ]
        },
        {
          "spine": 500,
          "outer_diameter": 0.1929,
          "gpi_weight": 6.9,
          "inner_diameter": 0.125,
          "length_options": [
            32.0
          ]
        },
        {
          "spine": 550,
          "outer_diameter": 0.1906,
          "gpi_weight": 6.5,
          "inner_diameter": 0.125,
          "length_options": [
            32.0
          ]
        },
        {
          "spine": 600,
          "outer_diameter": 0.1882,
          "gpi_weight": 6.1,
          "inner_diameter": 0.125,
          "length_options": [
            32.0
          ]
        },
        {
          "spine": 650,
          "outer_diameter": 0.1862,
          "gpi_weight": 5.83,
          "inner_diameter": 0.125,
          "length_options": [
            31.0
          ]
        },
        {
          "spine": 700,
          "outer_diameter": 0.1839,
          "gpi_weight": 5.55,
          "inner_diameter": 0.125,
          "length_options": [
            31.0
          ]
        },
        {
          "spine": 750,
          "outer_diameter": 0.1823,
          "gpi_weight": 5.31,
          "inner_diameter": 0.125,
          "length_options": [
            31.0
          ]
        },
        {
          "spine": 800,
          "outer_diameter": 0.1807,
          "gpi_weight": 5.06,
          "inner_diameter": 0.125,
          "length_options": [
            31.0
          ]
        },
        {
          "spine": 850,
          "outer_diameter": 0.1791,
          "gpi_weight": 4.94,
          "inner_diameter": 0.125,
          "length_options": [
            30.0
          ]
        },
        {
          "spine": 900,
          "outer_diameter": 0.1772,
          "gpi_weight": 4.81,
          "inner_diameter": 0.125,
          "length_options": [
            30.0
          ]
        },
        {
          "spine": 1000,
          "outer_diameter": 0.1752,
          "gpi_weight": 4.7,
          "inner_diameter": 0.125,
          "length_options": [
            30.0
          ]
        }
      ],
      "material": "40-TON Carbon",
      "carbon_content": null,
      "arrow_type": "target",
      "recommended_use": null,
      "description": "Ideal arrow with smaller diameter for less wind drift, high density carbon construction, available in full length shaft.",
      "straightness_tolerance": null,
      "weight_tolerance": null,
      "price_range": null,
      "availability": null,
      "source_url": "https://www.skylonarchery.com/arrows/id-3-2/paragon",
      "scraped_at": "2025-07-20T09:00:39.133066",
      "scraper_version": "1.0"
    },
    {
      "manufacturer": "Skylon Archery",
      "model_name": "Preminens",
      "spine_specifications": [
        {
          "spine": 350,
          "outer_diameter": 0.207,
          "gpi_weight": 8.47,
          "inner_diameter": 0.125,
          "length_options": [
            32.0
          ]
        },
        {
          "spine": 400,
          "outer_diameter": 0.204,
          "gpi_weight": 7.93,
          "inner_diameter": 0.125,
          "length_options": [
            32.0
          ]
        },
        {
          "spine": 450,
          "outer_diameter": 0.198,
          "gpi_weight": 7.42,
          "inner_diameter": 0.125,
          "length_options": [
            32.0
          ]
        },
        {
          "spine": 500,
          "outer_diameter": 0.193,
          "gpi_weight": 6.9,
          "inner_diameter": 0.125,
          "length_options": [
            32.0
          ]
        },
        {
          "spine": 550,
          "outer_diameter": 0.191,
          "gpi_weight": 6.5,
          "inner_diameter": 0.125,
          "length_options": [
            32.0
          ]
        },
        {
          "spine": 600,
          "outer_diameter": 0.188,
          "gpi_weight": 6.1,
          "inner_diameter": 0.125,
          "length_options": [
            32.0
          ]
        },
        {
          "spine": 650,
          "outer_diameter": 0.186,
          "gpi_weight": 5.83,
          "inner_diameter": 0.125,
          "length_options": [
            31.0
          ]
        }
      ],
      "material": "40-TON Carbon",
      "carbon_content": null,
      "arrow_type": "target",
      "recommended_use": null,
      "description": "Ideal arrow with smaller diameter for less wind drift and high-density carbon construction.",
      "straightness_tolerance": null,
      "weight_tolerance": null,
      "price_range": null,
      "availability": null,
      "source_url": "https://www.skylonarchery.com/arrows/id-3-2/preminens",
      "scraped_at": "2025-07-20T09:01:04.740825",
      "scraper_version": "1.0"
    },
    {
      "manufacturer": "Skylon Archery",
      "model_name": "Novice",
      "spine_specifications": [
        {
          "spine": 600,
          "outer_diameter": 0.225,
          "gpi_weight": 7.09,
          "inner_diameter": 0.166,
          "length_options": [
            31.0
          ]
        },
        {
          "spine": 700,
          "outer_diameter": 0.22,
          "gpi_weight": 6.17,
          "inner_diameter": 0.166,
          "length_options": [
            30.0
          ]
        },
        {
          "spine": 800,
          "outer_diameter": 0.216,
          "gpi_weight": 5.8,
          "inner_diameter": 0.166,
          "length_options": [
            30.0
          ]
        },
        {
          "spine": 900,
          "outer_diameter": 0.211,
          "gpi_weight": 5.34,
          "inner_diameter": 0.166,
          "length_options": [
            29.0
          ]
        },
        {
          "spine": 1000,
          "outer_diameter": 0.209,
          "gpi_weight": 4.9,
          "inner_diameter": 0.166,
          "length_options": [
            29.0
          ]
        },
        {
          "spine": 1100,
          "outer_diameter": 0.206,
          "gpi_weight": 4.64,
          "inner_diameter": 0.166,
          "length_options": [
            28.0
          ]
        },
        {
          "spine": 1300,
          "outer_diameter": 0.204,
          "gpi_weight": 4.16,
          "inner_diameter": 0.166,
          "length_options": [
            28.0
          ]
        },
        {
          "spine": 1500,
          "outer_diameter": 0.199,
          "gpi_weight": 4.0,
          "inner_diameter": 0.166,
          "length_options": [
            28.0
          ]
        },
        {
          "spine": 1800,
          "outer_diameter": 0.197,
          "gpi_weight": 3.89,
          "inner_diameter": 0.166,
          "length_options": [
            27.0
          ]
        },
        {
          "spine": 2000,
          "outer_diameter": 0.195,
          "gpi_weight": 3.6,
          "inner_diameter": 0.166,
          "length_options": [
            26.0
          ]
        }
      ],
      "material": "24-TON Carbon",
      "carbon_content": null,
      "arrow_type": "target",
      "recommended_use": null,
      "description": "Ideal arrow for beginners with full carbon construction and standard G diameter",
      "straightness_tolerance": null,
      "weight_tolerance": null,
      "price_range": null,
      "availability": null,
      "source_url": "https://www.skylonarchery.com/arrows/2023-06-29-08-52-09/novice",
      "scraped_at": "2025-07-20T09:01:36.264570",
      "scraper_version": "1.0"
    },
    {
      "manufacturer": "Skylon Archery",
      "model_name": "Radius",
      "spine_specifications": [
        {
          "spine": 400,
          "outer_diameter": 0.241,
          "gpi_weight": 9.47,
          "inner_diameter": 0.166,
          "length_options": [
            32.0
          ]
        },
        {
          "spine": 450,
          "outer_diameter": 0.236,
          "gpi_weight": 8.63,
          "inner_diameter": 0.166,
          "length_options": [
            32.0
          ]
        },
        {
          "spine": 500,
          "outer_diameter": 0.231,
          "gpi_weight": 8.0,
          "inner_diameter": 0.166,
          "length_options": [
            32.0
          ]
        },
        {
          "spine": 550,
          "outer_diameter": 0.227,
          "gpi_weight": 7.47,
          "inner_diameter": 0.166,
          "length_options": [
            32.0
          ]
        },
        {
          "spine": 600,
          "outer_diameter": 0.225,
          "gpi_weight": 7.09,
          "inner_diameter": 0.166,
          "length_options": [
            32.0
          ]
        },
        {
          "spine": 650,
          "outer_diameter": 0.22,
          "gpi_weight": 6.42,
          "inner_diameter": 0.166,
          "length_options": [
            32.0
          ]
        },
        {
          "spine": 700,
          "outer_diameter": 0.22,
          "gpi_weight": 6.17,
          "inner_diameter": 0.166,
          "length_options": [
            32.0
          ]
        },
        {
          "spine": 750,
          "outer_diameter": 0.217,
          "gpi_weight": 5.94,
          "inner_diameter": 0.166,
          "length_options": [
            32.0
          ]
        },
        {
          "spine": 800,
          "outer_diameter": 0.216,
          "gpi_weight": 5.8,
          "inner_diameter": 0.166,
          "length_options": [
            32.0
          ]
        },
        {
          "spine": 850,
          "outer_diameter": 0.213,
          "gpi_weight": 5.48,
          "inner_diameter": 0.166,
          "length_options": [
            32.0
          ]
        },
        {
          "spine": 900,
          "outer_diameter": 0.211,
          "gpi_weight": 5.34,
          "inner_diameter": 0.166,
          "length_options": [
            32.0
          ]
        },
        {
          "spine": 1000,
          "outer_diameter": 0.209,
          "gpi_weight": 4.9,
          "inner_diameter": 0.166,
          "length_options": [
            32.0
          ]
        },
        {
          "spine": 1100,
          "outer_diameter": 0.206,
          "gpi_weight": 4.64,
          "inner_diameter": 0.166,
          "length_options": [
            32.0
          ]
        },
        {
          "spine": 1300,
          "outer_diameter": 0.204,
          "gpi_weight": 4.16,
          "inner_diameter": 0.166,
          "length_options": [
            32.0
          ]
        },
        {
          "spine": 1500,
          "outer_diameter": 0.199,
          "gpi_weight": 4.0,
          "inner_diameter": 0.166,
          "length_options": [
            32.0
          ]
        },
        {
          "spine": 1800,
          "outer_diameter": 0.197,
          "gpi_weight": 3.89,
          "inner_diameter": 0.166,
          "length_options": [
            32.0
          ]
        },
        {
          "spine": 2000,
          "outer_diameter": 0.195,
          "gpi_weight": 3.6,
          "inner_diameter": 0.166,
          "length_options": [
            32.0
          ]
        }
      ],
      "material": "24-TON Carbon",
      "carbon_content": null,
      "arrow_type": "target",
      "recommended_use": null,
      "description": "Ideal arrow for standard G diameter, full carbon construction, full length shaft, uncut arrow",
      "straightness_tolerance": null,
      "weight_tolerance": null,
      "price_range": null,
      "availability": null,
      "source_url": "https://www.skylonarchery.com/arrows/2023-06-29-08-52-09/radius",
      "scraped_at": "2025-07-20T09:02:21.122520",
      "scraper_version": "1.0"
    },
    {
      "manufacturer": "Skylon Archery",
      "model_name": "Brixxon",
      "spine_specifications": [
        {
          "spine": 400,
          "outer_diameter": 0.2413,
          "gpi_weight": 9.47,
          "inner_diameter": 0.166,
          "length_options": [
            32.0
          ]
        },
        {
          "spine": 450,
          "outer_diameter": 0.2358,
          "gpi_weight": 8.63,
          "inner_diameter": 0.166,
          "length_options": [
            32.0
          ]
        },
        {
          "spine": 500,
          "outer_diameter": 0.2315,
          "gpi_weight": 8.0,
          "inner_diameter": 0.166,
          "length_options": [
            32.0
          ]
        },
        {
          "spine": 550,
          "outer_diameter": 0.2272,
          "gpi_weight": 7.47,
          "inner_diameter": 0.166,
          "length_options": [
            32.0
          ]
        },
        {
          "spine": 600,
          "outer_diameter": 0.2248,
          "gpi_weight": 7.09,
          "inner_diameter": 0.166,
          "length_options": [
            32.0
          ]
        },
        {
          "spine": 650,
          "outer_diameter": 0.2205,
          "gpi_weight": 6.42,
          "inner_diameter": 0.166,
          "length_options": [
            32.0
          ]
        },
        {
          "spine": 700,
          "outer_diameter": 0.2197,
          "gpi_weight": 6.17,
          "inner_diameter": 0.166,
          "length_options": [
            32.0
          ]
        },
        {
          "spine": 750,
          "outer_diameter": 0.2165,
          "gpi_weight": 5.94,
          "inner_diameter": 0.166,
          "length_options": [
            32.0
          ]
        },
        {
          "spine": 800,
          "outer_diameter": 0.2157,
          "gpi_weight": 5.8,
          "inner_diameter": 0.166,
          "length_options": [
            32.0
          ]
        },
        {
          "spine": 850,
          "outer_diameter": 0.2134,
          "gpi_weight": 5.48,
          "inner_diameter": 0.166,
          "length_options": [
            32.0
          ]
        },
        {
          "spine": 900,
          "outer_diameter": 0.211,
          "gpi_weight": 5.34,
          "inner_diameter": 0.166,
          "length_options": [
            32.0
          ]
        },
        {
          "spine": 1000,
          "outer_diameter": 0.2094,
          "gpi_weight": 4.9,
          "inner_diameter": 0.166,
          "length_options": [
            32.0
          ]
        },
        {
          "spine": 1100,
          "outer_diameter": 0.2055,
          "gpi_weight": 4.64,
          "inner_diameter": 0.166,
          "length_options": [
            32.0
          ]
        }
      ],
      "material": "24-TON Carbon",
      "carbon_content": null,
      "arrow_type": "target",
      "recommended_use": null,
      "description": "Ideal arrow for target archery with full carbon construction and standard G diameter.",
      "straightness_tolerance": null,
      "weight_tolerance": null,
      "price_range": null,
      "availability": null,
      "source_url": "https://www.skylonarchery.com/arrows/2023-06-29-08-52-09/brixxon",
      "scraped_at": "2025-07-20T09:02:59.685758",
      "scraper_version": "1.0"
    },
    {
      "manufacturer": "Skylon Archery",
      "model_name": "Instec",
      "spine_specifications": [
        {
          "spine": 300,
          "outer_diameter": 0.271,
          "gpi_weight": 9.44,
          "inner_diameter": 0.204,
          "length_options": [
            33.0
          ]
        },
        {
          "spine": 350,
          "outer_diameter": 0.265,
          "gpi_weight": 8.7,
          "inner_diameter": 0.204,
          "length_options": [
            33.0
          ]
        },
        {
          "spine": 400,
          "outer_diameter": 0.262,
          "gpi_weight": 8.16,
          "inner_diameter": 0.204,
          "length_options": [
            33.0
          ]
        },
        {
          "spine": 500,
          "outer_diameter": 0.254,
          "gpi_weight": 6.8,
          "inner_diameter": 0.204,
          "length_options": [
            33.0
          ]
        },
        {
          "spine": 600,
          "outer_diameter": 0.25,
          "gpi_weight": 6.19,
          "inner_diameter": 0.204,
          "length_options": [
            33.0
          ]
        },
        {
          "spine": 700,
          "outer_diameter": 0.244,
          "gpi_weight": 5.24,
          "inner_diameter": 0.204,
          "length_options": [
            33.0
          ]
        }
      ],
      "material": "24-TON Carbon",
      "carbon_content": null,
      "arrow_type": "target",
      "recommended_use": null,
      "description": "Ideal arrow for target archery with full carbon construction and smaller diameter.",
      "straightness_tolerance": null,
      "weight_tolerance": null,
      "price_range": null,
      "availability": null,
      "source_url": "https://www.skylonarchery.com/arrows/id-5-2/instec",
      "scraped_at": "2025-07-20T09:03:22.683312",
      "scraper_version": "1.0"
    },
    {
      "manufacturer": "Skylon Archery",
      "model_name": "Quantic",
      "spine_specifications": [
        {
          "spine": 300,
          "outer_diameter": 0.279,
          "gpi_weight": 10.92,
          "inner_diameter": 0.204,
          "length_options": [
            33.0
          ]
        },
        {
          "spine": 350,
          "outer_diameter": 0.272,
          "gpi_weight": 9.89,
          "inner_diameter": 0.204,
          "length_options": [
            33.0
          ]
        },
        {
          "spine": 400,
          "outer_diameter": 0.267,
          "gpi_weight": 9.0,
          "inner_diameter": 0.204,
          "length_options": [
            33.0
          ]
        },
        {
          "spine": 500,
          "outer_diameter": 0.261,
          "gpi_weight": 8.03,
          "inner_diameter": 0.204,
          "length_options": [
            33.0
          ]
        },
        {
          "spine": 600,
          "outer_diameter": 0.259,
          "gpi_weight": 7.65,
          "inner_diameter": 0.204,
          "length_options": [
            33.0
          ]
        },
        {
          "spine": 700,
          "outer_diameter": 0.252,
          "gpi_weight": 6.69,
          "inner_diameter": 0.204,
          "length_options": [
            33.0
          ]
        }
      ],
      "material": "24-TON 3K Carbon",
      "carbon_content": null,
      "arrow_type": "target",
      "recommended_use": null,
      "description": "Ideal arrow for target shooting with smaller diameter and full length shaft",
      "straightness_tolerance": null,
      "weight_tolerance": null,
      "price_range": null,
      "availability": null,
      "source_url": "https://www.skylonarchery.com/arrows/id-5-2/quantic",
      "scraped_at": "2025-07-20T09:03:44.662305",
      "scraper_version": "1.0"
    },
    {
      "manufacturer": "Skylon Archery",
      "model_name": "Ebony",
      "spine_specifications": [
        {
          "spine": 350,
          "outer_diameter": 0.265,
          "gpi_weight": 8.7,
          "inner_diameter": 0.204,
          "length_options": [
            33.0
          ]
        },
        {
          "spine": 400,
          "outer_diameter": 0.262,
          "gpi_weight": 8.16,
          "inner_diameter": 0.204,
          "length_options": [
            33.0
          ]
        },
        {
          "spine": 500,
          "outer_diameter": 0.254,
          "gpi_weight": 6.8,
          "inner_diameter": 0.204,
          "length_options": [
            33.0
          ]
        },
        {
          "spine": 600,
          "outer_diameter": 0.25,
          "gpi_weight": 6.19,
          "inner_diameter": 0.204,
          "length_options": [
            33.0
          ]
        },
        {
          "spine": 700,
          "outer_diameter": 0.244,
          "gpi_weight": 5.24,
          "inner_diameter": 0.204,
          "length_options": [
            33.0
          ]
        }
      ],
      "material": "24-TON Carbon",
      "carbon_content": null,
      "arrow_type": "target",
      "recommended_use": null,
      "description": "Ideal arrow for target archery with full carbon construction and uncut shaft.",
      "straightness_tolerance": null,
      "weight_tolerance": null,
      "price_range": null,
      "availability": null,
      "source_url": "https://www.skylonarchery.com/arrows/id-5-2/ebony",
      "scraped_at": "2025-07-20T09:04:04.772682",
      "scraper_version": "1.0"
    },
    {
      "manufacturer": "Skylon Archery",
      "model_name": "Backbone",
      "spine_specifications": [
        {
          "spine": 350,
          "outer_diameter": 0.272,
          "gpi_weight": 9.9,
          "inner_diameter": 0.204,
          "length_options": [
            33.0
          ]
        },
        {
          "spine": 400,
          "outer_diameter": 0.267,
          "gpi_weight": 9.0,
          "inner_diameter": 0.204,
          "length_options": [
            33.0
          ]
        },
        {
          "spine": 500,
          "outer_diameter": 0.261,
          "gpi_weight": 7.9,
          "inner_diameter": 0.204,
          "length_options": [
            33.0
          ]
        },
        {
          "spine": 600,
          "outer_diameter": 0.259,
          "gpi_weight": 7.4,
          "inner_diameter": 0.204,
          "length_options": [
            33.0
          ]
        },
        {
          "spine": 700,
          "outer_diameter": 0.252,
          "gpi_weight": 6.7,
          "inner_diameter": 0.204,
          "length_options": [
            33.0
          ]
        }
      ],
      "material": "24-TON Carbon 3K",
      "carbon_content": null,
      "arrow_type": "target",
      "recommended_use": null,
      "description": "Ideal arrow for target archery with smaller diameter and full length shaft.",
      "straightness_tolerance": null,
      "weight_tolerance": null,
      "price_range": null,
      "availability": null,
      "source_url": "https://www.skylonarchery.com/arrows/id-5-2/backbone",
      "scraped_at": "2025-07-20T09:04:25.028631",
      "scraper_version": "1.0"
    },
    {
      "manufacturer": "Skylon Archery",
      "model_name": "Savage",
      "spine_specifications": [
        {
          "spine": 350,
          "outer_diameter": 0.291,
          "gpi_weight": 7.9,
          "inner_diameter": 0.244,
          "length_options": [
            30.0
          ]
        },
        {
          "spine": 400,
          "outer_diameter": 0.29,
          "gpi_weight": 7.4,
          "inner_diameter": 0.244,
          "length_options": [
            30.0
          ]
        },
        {
          "spine": 500,
          "outer_diameter": 0.285,
          "gpi_weight": 6.5,
          "inner_diameter": 0.244,
          "length_options": [
            30.0
          ]
        }
      ],
      "material": "24-TON Carbon",
      "carbon_content": null,
      "arrow_type": "target",
      "recommended_use": null,
      "description": "Ideal arrow for target archery with full carbon construction",
      "straightness_tolerance": null,
      "weight_tolerance": null,
      "price_range": null,
      "availability": null,
      "source_url": "https://www.skylonarchery.com/arrows/id-6-2/savage",
      "scraped_at": "2025-07-20T09:04:46.728137",
      "scraper_version": "1.0"
    },
    {
      "manufacturer": "Skylon Archery",
      "model_name": "Edge",
      "spine_specifications": [
        {
          "spine": 300,
          "outer_diameter": 0.2972,
          "gpi_weight": 8.5,
          "inner_diameter": 0.244,
          "length_options": [
            33.0
          ]
        },
        {
          "spine": 350,
          "outer_diameter": 0.291,
          "gpi_weight": 7.61,
          "inner_diameter": 0.244,
          "length_options": [
            33.0
          ]
        },
        {
          "spine": 400,
          "outer_diameter": 0.2894,
          "gpi_weight": 7.33,
          "inner_diameter": 0.244,
          "length_options": [
            33.0
          ]
        },
        {
          "spine": 500,
          "outer_diameter": 0.2803,
          "gpi_weight": 5.8,
          "inner_diameter": 0.244,
          "length_options": [
            33.0
          ]
        },
        {
          "spine": 600,
          "outer_diameter": 0.2776,
          "gpi_weight": 5.58,
          "inner_diameter": 0.244,
          "length_options": [
            33.0
          ]
        },
        {
          "spine": 700,
          "outer_diameter": 0.2756,
          "gpi_weight": 5.12,
          "inner_diameter": 0.244,
          "length_options": [
            33.0
          ]
        },
        {
          "spine": 800,
          "outer_diameter": 0.2697,
          "gpi_weight": 4.2,
          "inner_diameter": 0.244,
          "length_options": [
            33.0
          ]
        }
      ],
      "material": "24-TON Carbon",
      "carbon_content": null,
      "arrow_type": "target",
      "recommended_use": null,
      "description": "Ideal arrow for target archery with full carbon construction and standard S diameter.",
      "straightness_tolerance": null,
      "weight_tolerance": null,
      "price_range": null,
      "availability": null,
      "source_url": "https://www.skylonarchery.com/arrows/id-6-2/edge",
      "scraped_at": "2025-07-20T09:05:11.441010",
      "scraper_version": "1.0"
    },
    {
      "manufacturer": "Skylon Archery",
      "model_name": "Maverick",
      "spine_specifications": [
        {
          "spine": 300,
          "outer_diameter": 0.306,
          "gpi_weight": 10.21,
          "inner_diameter": 0.244,
          "length_options": [
            33.0
          ]
        },
        {
          "spine": 350,
          "outer_diameter": 0.303,
          "gpi_weight": 9.4,
          "inner_diameter": 0.244,
          "length_options": [
            33.0
          ]
        },
        {
          "spine": 400,
          "outer_diameter": 0.297,
          "gpi_weight": 8.6,
          "inner_diameter": 0.244,
          "length_options": [
            33.0
          ]
        },
        {
          "spine": 500,
          "outer_diameter": 0.292,
          "gpi_weight": 7.7,
          "inner_diameter": 0.244,
          "length_options": [
            33.0
          ]
        }
      ],
      "material": "24-TON 3K Carbon",
      "carbon_content": null,
      "arrow_type": "target",
      "recommended_use": null,
      "description": "Ideal arrow for target archery with full length shaft and uncut arrow options.",
      "straightness_tolerance": null,
      "weight_tolerance": null,
      "price_range": null,
      "availability": null,
      "source_url": "https://www.skylonarchery.com/arrows/id-6-2/maverick",
      "scraped_at": "2025-07-20T09:05:30.153788",
      "scraper_version": "1.0"
    },
    {
      "manufacturer": "Skylon Archery",
      "model_name": "Rove",
      "spine_specifications": [
        {
          "spine": 300,
          "outer_diameter": 0.303,
          "gpi_weight": 9.68,
          "inner_diameter": 0.244,
          "length_options": [
            33.0
          ]
        },
        {
          "spine": 350,
          "outer_diameter": 0.293,
          "gpi_weight": 7.89,
          "inner_diameter": 0.244,
          "length_options": [
            33.0
          ]
        },
        {
          "spine": 400,
          "outer_diameter": 0.291,
          "gpi_weight": 7.73,
          "inner_diameter": 0.244,
          "length_options": [
            33.0
          ]
        },
        {
          "spine": 500,
          "outer_diameter": 0.29,
          "gpi_weight": 7.25,
          "inner_diameter": 0.244,
          "length_options": [
            33.0
          ]
        }
      ],
      "material": "24-TON Carbon",
      "carbon_content": null,
      "arrow_type": "target",
      "recommended_use": null,
      "description": "Ideal arrow for target archery with full carbon construction and standard S diameter.",
      "straightness_tolerance": null,
      "weight_tolerance": null,
      "price_range": null,
      "availability": null,
      "source_url": "https://www.skylonarchery.com/arrows/id-6-2/rove",
      "scraped_at": "2025-07-20T09:05:50.319689",
      "scraper_version": "1.0"
    },
    {
      "manufacturer": "Skylon Archery",
      "model_name": "Phoric",
      "spine_specifications": [
        {
          "spine": 350,
          "outer_diameter": 0.292,
          "gpi_weight": 7.4,
          "inner_diameter": 0.244,
          "length_options": [
            33.0
          ]
        },
        {
          "spine": 400,
          "outer_diameter": 0.289,
          "gpi_weight": 6.9,
          "inner_diameter": 0.244,
          "length_options": [
            33.0
          ]
        },
        {
          "spine": 500,
          "outer_diameter": 0.28,
          "gpi_weight": 6.0,
          "inner_diameter": 0.244,
          "length_options": [
            33.0
          ]
        },
        {
          "spine": 600,
          "outer_diameter": 0.278,
          "gpi_weight": 5.7,
          "inner_diameter": 0.244,
          "length_options": [
            33.0
          ]
        },
        {
          "spine": 700,
          "outer_diameter": 0.276,
          "gpi_weight": 5.4,
          "inner_diameter": 0.244,
          "length_options": [
            33.0
          ]
        }
      ],
      "material": "24-TON Carbon",
      "carbon_content": null,
      "arrow_type": "target",
      "recommended_use": null,
      "description": "Ideal arrow for target archery with full carbon construction and standard S diameter.",
      "straightness_tolerance": null,
      "weight_tolerance": null,
      "price_range": null,
      "availability": null,
      "source_url": "https://www.skylonarchery.com/arrows/id-6-2/phoric",
      "scraped_at": "2025-07-20T09:06:11.310118",
      "scraper_version": "1.0"
    },
    {
      "manufacturer": "Skylon Archery",
      "model_name": "Frontier",
      "spine_specifications": [
        {
          "spine": 300,
          "outer_diameter": 0.297,
          "gpi_weight": 8.5,
          "inner_diameter": 0.244,
          "length_options": [
            33.0
          ]
        },
        {
          "spine": 350,
          "outer_diameter": 0.291,
          "gpi_weight": 7.61,
          "inner_diameter": 0.244,
          "length_options": [
            33.0
          ]
        },
        {
          "spine": 400,
          "outer_diameter": 0.289,
          "gpi_weight": 7.33,
          "inner_diameter": 0.244,
          "length_options": [
            33.0
          ]
        },
        {
          "spine": 500,
          "outer_diameter": 0.28,
          "gpi_weight": 5.8,
          "inner_diameter": 0.244,
          "length_options": [
            33.0
          ]
        },
        {
          "spine": 600,
          "outer_diameter": 0.278,
          "gpi_weight": 5.58,
          "inner_diameter": 0.244,
          "length_options": [
            33.0
          ]
        },
        {
          "spine": 700,
          "outer_diameter": 0.276,
          "gpi_weight": 5.12,
          "inner_diameter": 0.244,
          "length_options": [
            33.0
          ]
        },
        {
          "spine": 800,
          "outer_diameter": 0.27,
          "gpi_weight": 4.2,
          "inner_diameter": 0.244,
          "length_options": [
            33.0
          ]
        }
      ],
      "material": "24-TON Carbon",
      "carbon_content": null,
      "arrow_type": "target",
      "recommended_use": null,
      "description": "Ideal arrow for target archery with full carbon construction and standard S diameter.",
      "straightness_tolerance": null,
      "weight_tolerance": null,
      "price_range": null,
      "availability": null,
      "source_url": "https://www.skylonarchery.com/arrows/id-6-2/frontier",
      "scraped_at": "2025-07-20T09:06:36.100749",
      "scraper_version": "1.0"
    },
    {
      "manufacturer": "Skylon Archery",
      "model_name": "Bentwood",
      "spine_specifications": [
        {
          "spine": 300,
          "outer_diameter": 0.303,
          "gpi_weight": 9.68,
          "inner_diameter": 0.244,
          "length_options": [
            33.0
          ]
        },
        {
          "spine": 350,
          "outer_diameter": 0.293,
          "gpi_weight": 7.89,
          "inner_diameter": 0.244,
          "length_options": [
            33.0
          ]
        },
        {
          "spine": 400,
          "outer_diameter": 0.291,
          "gpi_weight": 7.73,
          "inner_diameter": 0.244,
          "length_options": [
            33.0
          ]
        },
        {
          "spine": 500,
          "outer_diameter": 0.29,
          "gpi_weight": 7.25,
          "inner_diameter": 0.244,
          "length_options": [
            33.0
          ]
        },
        {
          "spine": 600,
          "outer_diameter": 0.282,
          "gpi_weight": 5.87,
          "inner_diameter": 0.244,
          "length_options": [
            33.0
          ]
        },
        {
          "spine": 700,
          "outer_diameter": 0.28,
          "gpi_weight": 5.7,
          "inner_diameter": 0.244,
          "length_options": [
            33.0
          ]
        },
        {
          "spine": 800,
          "outer_diameter": 0.276,
          "gpi_weight": 5.4,
          "inner_diameter": 0.244,
          "length_options": [
            33.0
          ]
        }
      ],
      "material": "24-TON Carbon",
      "carbon_content": null,
      "arrow_type": "target",
      "recommended_use": null,
      "description": "Ideal arrow for target archery with full carbon construction and standard S diameter.",
      "straightness_tolerance": null,
      "weight_tolerance": null,
      "price_range": null,
      "availability": null,
      "source_url": "https://www.skylonarchery.com/arrows/id-6-2/bentwood",
      "scraped_at": "2025-07-20T09:07:00.872016",
      "scraper_version": "1.0"
    },
    {
      "manufacturer": "Skylon Archery",
      "model_name": "Bruxx",
      "spine_specifications": [
        {
          "spine": 300,
          "outer_diameter": 0.355,
          "gpi_weight": 8.52,
          "inner_diameter": 0.315,
          "length_options": [
            33.0
          ]
        },
        {
          "spine": 350,
          "outer_diameter": 0.353,
          "gpi_weight": 7.92,
          "inner_diameter": 0.315,
          "length_options": [
            33.0
          ]
        },
        {
          "spine": 400,
          "outer_diameter": 0.352,
          "gpi_weight": 7.42,
          "inner_diameter": 0.315,
          "length_options": [
            33.0
          ]
        },
        {
          "spine": 500,
          "outer_diameter": 0.348,
          "gpi_weight": 6.61,
          "inner_diameter": 0.315,
          "length_options": [
            33.0
          ]
        }
      ],
      "material": "24-TON Carbon",
      "carbon_content": null,
      "arrow_type": "target",
      "recommended_use": null,
      "description": "Ideal arrow for target archery with full carbon construction and maximum diameter for World Archery compliance.",
      "straightness_tolerance": null,
      "weight_tolerance": null,
      "price_range": null,
      "availability": null,
      "source_url": "https://www.skylonarchery.com/arrows/id-8-0/bruxx",
      "scraped_at": "2025-07-20T09:07:19.713033",
      "scraper_version": "1.0"
    },
    {
      "manufacturer": "Skylon Archery",
      "model_name": "Empros",
      "spine_specifications": [
        {
          "spine": 300,
          "outer_diameter": 0.362,
          "gpi_weight": 9.5,
          "inner_diameter": 0.315,
          "length_options": [
            33.0
          ]
        },
        {
          "spine": 350,
          "outer_diameter": 0.358,
          "gpi_weight": 8.69,
          "inner_diameter": 0.315,
          "length_options": [
            33.0
          ]
        },
        {
          "spine": 400,
          "outer_diameter": 0.357,
          "gpi_weight": 8.49,
          "inner_diameter": 0.315,
          "length_options": [
            33.0
          ]
        },
        {
          "spine": 500,
          "outer_diameter": 0.353,
          "gpi_weight": 7.27,
          "inner_diameter": 0.315,
          "length_options": [
            33.0
          ]
        }
      ],
      "material": "24-TON 3K Carbon",
      "carbon_content": null,
      "arrow_type": "target",
      "recommended_use": null,
      "description": "Ideal arrow for target archery with full carbon construction and maximum diameter compliance.",
      "straightness_tolerance": null,
      "weight_tolerance": null,
      "price_range": null,
      "availability": null,
      "source_url": "https://www.skylonarchery.com/arrows/id-8-0/empros",
      "scraped_at": "2025-07-20T09:07:39.168626",
      "scraper_version": "1.0"
    }
  ],
  "failed_urls": [
    {
      "url": "https://www.skylonarchery.com/arrows/id-6-2/fast-wing",
      "manufacturer": "Skylon Archery",
      "reason": "No data extracted"
    }
  ]
}